{
	"id": "60775b68-9285-48a8-bb20-149bbdfac2ac",
	"name": "Local",
	"values": [
		{
			"key": "superdomain",
			"value": "{{MachineName}}.dev",
			"description": "",
			"enabled": true
		},
		{
			"key": "Site",
			"value": "https://{{superdomain}}.onenote-int.com",
			"description": "",
			"enabled": true
		},
		{
			"key": "version",
			"value": "beta",
			"description": "",
			"enabled": true
		}
	],
	"_postman_variable_scope": "environment",
	"_postman_exported_at": "2018-10-15T18:24:50.465Z",
	"_postman_exported_using": "Postman/6.4.2"
}